emreclass.py
genie_parsers.py
runemre.py
emre-1.0.14.dist-info/LICENSE
emre-1.0.14.dist-info/METADATA
emre-1.0.14.dist-info/WHEEL
emre-1.0.14.dist-info/entry_points.txt
emre-1.0.14.dist-info/top_level.txt
emre-1.0.14.dist-info/RECORD
