Metadata-Version: 2.1
Name: emre
Version: 1.0.14
Summary: Embedded Machine Reasoning
Home-page: https://github.com/pypa/sampleproject
Author: Peter Van Horne
Author-email: petervh@cisco.com
License: UNKNOWN
Platform: UNKNOWN
Classifier: Programming Language :: Python :: 3
Classifier: License :: OSI Approved :: MIT License
Classifier: Operating System :: OS Independent
Requires-Python: >=3.6
Requires-Dist: ncclient (==0.6.9)
Requires-Dist: clipspy (==0.3.3)
Requires-Dist: xmltodict
Requires-Dist: pexpect
Requires-Dist: regex
